kyoto_sightseeing/__init__.py
kyoto_sightseeing/coordinates.py
kyoto_sightseeing/gui.py
kyoto_sightseeing/route_planner.py
kyoto_sightseeing-0.1.dist-info/METADATA
kyoto_sightseeing-0.1.dist-info/WHEEL
kyoto_sightseeing-0.1.dist-info/entry_points.txt
kyoto_sightseeing-0.1.dist-info/top_level.txt
kyoto_sightseeing-0.1.dist-info/RECORD
